index_safe/__init__.py
index_safe/benchmark.py
index_safe/burst.xsl
index_safe/create_index.py
index_safe/extract_burst.py
index_safe/extract_metadata.py
index_safe/invoke_extract_lambda.py
index_safe/invoke_index_lambda.py
index_safe/utils.py
index_safe-0.2.1.dist-info/METADATA
index_safe-0.2.1.dist-info/WHEEL
index_safe-0.2.1.dist-info/entry_points.txt
index_safe-0.2.1.dist-info/top_level.txt
index_safe-0.2.1.dist-info/RECORD
