Metadata-Version: 2.1
Name: index_safe
Version: 0.2.1
Summary: Index Sentinel-1 SAFE for fast burst data and metdata download
Author-email: Forrest Williams <ffwilliams2@alaska.edu>
Project-URL: Homepage, https://github.com/forrestfwilliams/indexed_safe
Project-URL: Bug Tracker, https://github.com/forrestfwilliams/indexed_safe/issues
Classifier: Intended Audience :: Science/Research
Classifier: Natural Language :: English
Classifier: Operating System :: OS Independent
Classifier: Programming Language :: Python :: 3
Classifier: Programming Language :: Python :: 3.8
Classifier: Programming Language :: Python :: 3.9
Classifier: Programming Language :: Python :: 3.10
Requires-Python: >=3.8
Requires-Dist: gdal
Requires-Dist: boto3
Requires-Dist: tqdm
Requires-Dist: numpy
Requires-Dist: requests
Requires-Dist: lxml
Provides-Extra: develop
Requires-Dist: pytest ; extra == 'develop'
